odoo/addons/auto_set_everybody_calendar/__init__.py
odoo/addons/auto_set_everybody_calendar/__manifest__.py
odoo/addons/auto_set_everybody_calendar/static/src/js/auto_set_everybody_calendar_script.js
odoo/addons/auto_set_everybody_calendar/views/assets.xml
odoo12_addon_auto_set_everybody_calendar-12.0.1.0.2.dist-info/METADATA
odoo12_addon_auto_set_everybody_calendar-12.0.1.0.2.dist-info/WHEEL
odoo12_addon_auto_set_everybody_calendar-12.0.1.0.2.dist-info/top_level.txt
odoo12_addon_auto_set_everybody_calendar-12.0.1.0.2.dist-info/RECORD
