Metadata-Version: 2.1
Name: odoo12-addon-auto-set-everybody-calendar
Version: 12.0.1.0.2
Summary: In Calendar main view auto toggles checkboxes (Everything, Everybody)
Home-page: https://coopdevs.org
Author: Coopdevs Treball SCCL
License: AGPL-3
Platform: UNKNOWN
Classifier: Programming Language :: Python
Classifier: Framework :: Odoo
Classifier: License :: OSI Approved :: GNU Affero General Public License v3
Requires-Python: >=3.5
Requires-Dist: odoo (<12.1dev,>=12.0a)
